pygslv.cpython-310-x86_64-linux-gnu.so
pygslv-0.4.15.dist-info/licenses/LICENSE.txt
pygslv-stubs/__init__.pyi
pygslv-0.4.15.dist-info/METADATA
pygslv-0.4.15.dist-info/WHEEL
pygslv-0.4.15.dist-info/top_level.txt
pygslv-0.4.15.dist-info/RECORD
