Metadata-Version: 2.4
Name: pygslv
Version: 0.4.15
Summary: gslv
Home-page: https://www.eRoots.tech
Author: eRoots
Author-email: 
Keywords: power systems simulation
Classifier: Programming Language :: Python :: 3.12
License-File: LICENSE.txt
Requires-Dist: numpy
Requires-Dist: scipy
Dynamic: author
Dynamic: classifier
Dynamic: description
Dynamic: home-page
Dynamic: keywords
Dynamic: license-file
Dynamic: requires-dist
Dynamic: summary
